[
    {
        "id": 114,
        "question": "Benzin, gaz yağı, mazot vb. sıvı yakıt",
        "letter": "A",
        "answer": "akaryakıt"
    },
    {
        "id": 1083,
        "question": "Erkek kümes hayvanlarının en iri ve yaşlı olanı",
        "letter": "B",
        "answer": "Babaç"
    },
    {
        "id": 1373,
        "question": "Bir ülkede yönetime el koyan kimselerden oluşan kurul",
        "letter": "C",
        "answer": "Cunta, cuntacılar, cunta kurulu"
    },
    {
        "id": 1449,
        "question": "Diz kapaklarına kadar çıkan bir çeşit ayakkabı",
        "letter": "Ç",
        "answer": "Çizme"
    },
    {
        "id": 184,
        "question": "Zihinde beliren olayların, düşüncelerin bütünü, rüya",
        "letter": "D",
        "answer": "düş"
    },
    {
        "id": 1236,
        "question": "Gizlerle, sırlarla örtülü olan, gizemli",
        "letter": "E",
        "answer": "Esrarengiz"
    },
    {
        "id": 220,
        "question": "Belirli nesneler veya durumlar karşısında duyulan olağan dışı güçlü korku",
        "letter": "F",
        "answer": "fobi"
    },
    {
        "id": 230,
        "question": "Tasa, kaygı, üzüntü",
        "letter": "G",
        "answer": "gam"
    },
    {
        "id": 252,
        "question": "Niteliği değişmemiş, aslına uygun olan",
        "letter": "H",
        "answer": "hakiki"
    },
    {
        "id": 1810,
        "question": "BİR KURUM VEYA KURULUŞUN YÖNETİLDİĞİ YER VEYA MAKAM",
        "letter": "İ",
        "answer": "İdare, İdari işler, İdari daire"
    },
    {
        "id": 612,
        "question": "Isıtmada kullanılan yakıtı düzenli ve ayarlı biçimde yakan araç",
        "letter": "K",
        "answer": "Kombi"
    },
    {
        "id": 1455,
        "question": "Eklembacaklılarda yaşamın ilk evresi",
        "letter": "L",
        "answer": "Larva, larva dönemi"
    },
    {
        "id": 818,
        "question": "Eski zamanların tek kişilik komedi gösterisi ustası",
        "letter": "M",
        "answer": "Meddah"
    },
    {
        "id": 929,
        "question": "Tek ağızlı balta",
        "letter": "N",
        "answer": "Nacak"
    },
    {
        "id": 1889,
        "question": "KAVİMLER GÖÇÜYLE BAŞLAYAN TARİHİ DÖNEM",
        "letter": "O",
        "answer": "Ortaçağ"
    },
    {
        "id": 1482,
        "question": "Bir yargıya varmak veya değer vermek için başvurulan ilke, kıstas, mısdak, kriter",
        "letter": "Ö",
        "answer": "Ölçüt"
    },
    {
        "id": 667,
        "question": "Yalnız ad ve soyadının baş harfleriyle atılan kısa imza",
        "letter": "P",
        "answer": "Paraf, paraf atma, paraf atmak"
    },
    {
        "id": 1906,
        "question": "BASKETBOLDA, SAYI OLMAYAN BİR ATIŞTAN SONRA POTADAN SEKEN TOPUN HAVADAYKEN YAKALANMASI",
        "letter": "R",
        "answer": "Ribaund"
    },
    {
        "id": 687,
        "question": "Tarımsal yapay iklim alanı",
        "letter": "S",
        "answer": "Sera"
    },
    {
        "id": 1678,
        "question": "Almanya ve Avusturya'da hükûmet başkanı ünvanı",
        "letter": "Ş",
        "answer": "Şansölye"
    },
    {
        "id": 1882,
        "question": "PİYASALARDA, BELİRLİ BİR MAL VE HİZMETE YÖNELEN SATIN ALMA İSTEĞİ",
        "letter": "T",
        "answer": "Talep"
    },
    {
        "id": 1068,
        "question": "Çok uzun",
        "letter": "U",
        "answer": "upuzun"
    },
    {
        "id": 1507,
        "question": "Canlı, doğup çoğalmak",
        "letter": "Ü",
        "answer": "Üremek"
    },
    {
        "id": 1251,
        "question": "Orta, iki şeyin ortasında olan, ortalama",
        "letter": "V",
        "answer": "Vasat"
    },
    {
        "id": 840,
        "question": "Akarsuyun aktığı yer, mecra",
        "letter": "Y",
        "answer": "Yatak, yatağı"
    },
    {
        "id": 738,
        "question": "Boşuna harcama, zarar",
        "letter": "Z",
        "answer": "Ziyan, ziyan etme, ziyan etmek"
    }
]