[
    {
        "id": 1081,
        "question": "Masa başında uydurulup gerçekmiş gibi yayımlanan yalan haber",
        "letter": "A",
        "answer": "Asparagas, asparagas haber"
    },
    {
        "id": 1220,
        "question": "Atış bilimi, mermi ve füzelerin hareketlerini inceleyen bir bilim dalı",
        "letter": "B",
        "answer": "Balistik, balistik bilimi"
    },
    {
        "id": 1309,
        "question": "Canlı, neşeli ve sokulgan",
        "letter": "C",
        "answer": "Civelek"
    },
    {
        "id": 183,
        "question": "Oy vermekten, eğilim göstermekten veya bir şey yapmaktan kaçınan, kararsız kimse",
        "letter": "Ç",
        "answer": "çekimser"
    },
    {
        "id": 194,
        "question": "Açık sözlü",
        "letter": "D",
        "answer": "dobra"
    },
    {
        "id": 79,
        "question": "Kırkpınar yağlı güreşlerinin yapıldığı ilimiz",
        "letter": "E",
        "answer": "edirne"
    },
    {
        "id": 1968,
        "question": "KURAL İHLALİ SONRASI, KALEYE DOĞRUDAN ŞUT ÇEKİLEN SERBEST VURUŞ",
        "letter": "F",
        "answer": "FRİKİK"
    },
    {
        "id": 582,
        "question": "Dikkatli ve planlı olarak ele alınıp incelenme durumu",
        "letter": "G",
        "answer": "Gözlem, Gözlem yapma, Gözlem yapmak"
    },
    {
        "id": 807,
        "question": "İçe dert olan hayal kırıklığı, düşyıkımı",
        "letter": "H",
        "answer": "Hüsran"
    },
    {
        "id": 1712,
        "question": "Bilgisayarların veri işleyen ve yazılım komutlarını gerçekleştiren devre elemanı",
        "letter": "İ",
        "answer": "İşlemci"
    },
    {
        "id": 1288,
        "question": "Mukayese etmek, karşılaştırmak",
        "letter": "K",
        "answer": "Kıyaslamak, kıyaslama, kıyas yapma, kıyas yapmak"
    },
    {
        "id": 291,
        "question": "Yeterince aydınlık olmayan, yarı karanlık, az ışık alan",
        "letter": "L",
        "answer": "loş"
    },
    {
        "id": 628,
        "question": "Ruh hali, mizaç, hal, anlık hal durumu",
        "letter": "M",
        "answer": "Mod, moral"
    },
    {
        "id": 1275,
        "question": "Geçmişteki anıların ve olayların özlemini duyma durumu",
        "letter": "N",
        "answer": "Nostalji, nostaliji"
    },
    {
        "id": 342,
        "question": "Uygun bulma, tasdik, icazet, izin",
        "letter": "O",
        "answer": "onay, onaylama, onaylamak"
    },
    {
        "id": 660,
        "question": "Bir kuruluşa bağlı alt bölümlerin bütünü, teşkilat",
        "letter": "Ö",
        "answer": "Örgüt"
    },
    {
        "id": 673,
        "question": "Söz dalaşı",
        "letter": "P",
        "answer": "Polemik"
    },
    {
        "id": 395,
        "question": "Orta kaldırım",
        "letter": "R",
        "answer": "refüj"
    },
    {
        "id": 1948,
        "question": "MECAZEN, “AKIL SAĞLIĞINI YİTİRMEK” ANLAMINA GELEN SÖZ",
        "letter": "S",
        "answer": "Sıyırma, Sıyırmak"
    },
    {
        "id": 423,
        "question": "Bir çıkar karşılığı, uzlaşarak bir iş yapma, aldatma",
        "letter": "Ş",
        "answer": "şike, şike yapma, şike yapmak"
    },
    {
        "id": 1771,
        "question": "KENDİSİ HASTALANMADAN O HASTALIĞIN SEBEBİ OLAN MİKROBU BAŞKASINA BULAŞTIRAN KİMSE VEYA HAYVAN",
        "letter": "T",
        "answer": "Taşıyıcı"
    },
    {
        "id": 37,
        "question": "Belli bir işte belli bir konuda bilgili olan (kimse)",
        "letter": "U",
        "answer": "Uzman, Usta"
    },
    {
        "id": 1473,
        "question": "Oyunda, yenilmek, kaybetmek",
        "letter": "Ü",
        "answer": "Ütülmek"
    },
    {
        "id": 771,
        "question": "Araç, taşıt anlamlarındaki söz",
        "letter": "V",
        "answer": "Vasıta"
    },
    {
        "id": 1936,
        "question": "Doğum tarihi ve saati dikkate alınarak yapılan hesaplama ile ortaya çıkan burç",
        "letter": "Y",
        "answer": "Yükselen, Yükselen burç"
    },
    {
        "id": 502,
        "question": "Aldatıcı şey, tuzak, hile",
        "letter": "Z",
        "answer": "zoka"
    }
]